pyproffx
