Metadata-Version: 1.1
Name: pyproffx
Version: 0.9.3
Summary: A tool set of python modules for profile data analysis on Fujitsu's PRIMEHPC FX10 supercomputer
Home-page: http://github.com/halm/pyproffx
Author: Haruhiko Matsuo
Author-email: halm.matsuo@gmail.com
License: MIT
Download-URL: https://github.com/halm/pyproffx/tarball/0.9.3
Keywords: hpc,profiler
Platform: UNKNOWN
